jynx/__init__.py
jynx/callbacks.py
jynx/fit.py
jynx/layers/__init__.py
jynx/layers/containers.py
jynx/layers/factory.py
jynx/layers/linear.py
jynx/layers/misc.py
jynx/layers/module.py
jynx/layers/moe.py
jynx/layers/nets.py
jynx/layers/rnn.py
jynx/layers/static.py
jynx/layers/transformer.py
jynx/pytree.py
jax_jynx-0.3.1.dist-info/LICENSE
jax_jynx-0.3.1.dist-info/METADATA
jax_jynx-0.3.1.dist-info/WHEEL
jax_jynx-0.3.1.dist-info/RECORD
