Metadata-Version: 2.1
Name: jax-jynx
Version: 0.3.1
Summary: A neural network library using jax
Author: Scott Cameron
Requires-Python: >=3.12
Classifier: Programming Language :: Python :: 3
Classifier: Programming Language :: Python :: 3.12
Requires-Dist: jax (>=0.4.27)
Requires-Dist: jaxlib (>=0.4.24)
Requires-Dist: optax (>=0.1.9)
